agda-2.7.0.1.dist-info/RECORD
agda-2.7.0.1.dist-info/LICENSE
agda-2.7.0.1.dist-info/WHEEL
agda-2.7.0.1.dist-info/entry_points.txt
agda-2.7.0.1.dist-info/top_level.txt
agda-2.7.0.1.dist-info/METADATA
agda/Binding.hs
agda/__init__.py
agda/_binding.pyi
agda/_binding.cpython-310-darwin.so
agda/binding.def
agda/binding.i
agda/_binding.py
agda/Paths_Agda.hs
agda/__main__.py
agda/mode/__init__.py
agda/mode/__main__.py
