Metadata-Version: 2.2
Name: agda
Version: 2.7.0.1
Summary: A project that packages Agda as a Python package.
Author-email: Wen Kokke <wenkokke@users.noreply.github.com>
License: MIT License
Classifier: License :: OSI Approved :: MIT License
Classifier: Operating System :: MacOS
Classifier: Operating System :: Microsoft :: Windows
Classifier: Operating System :: POSIX :: Linux
Classifier: Programming Language :: Python :: 3.7
Classifier: Programming Language :: Python :: 3.8
Classifier: Programming Language :: Python :: 3.9
Classifier: Programming Language :: Python :: 3.10
Classifier: Programming Language :: Python :: 3.11
Classifier: Programming Language :: Python :: 3.12
Classifier: Programming Language :: Python :: 3.13
Classifier: Programming Language :: Python :: Implementation :: CPython
Requires-Python: <3.14,>=3.7.1
License-File: LICENSE
Provides-Extra: mypy
Requires-Dist: types_setuptools>=45; extra == "mypy"
Provides-Extra: test
Requires-Dist: pytest<9,>=7.1; extra == "test"
